pycricinfo/__init__.py
pycricinfo/config.py
pycricinfo/exceptions.py
pycricinfo/output.py
pycricinfo/utils.py
pycricinfo/api/__init__.py
pycricinfo/api/server.py
pycricinfo/api/endpoints/__init__.py
pycricinfo/api/endpoints/match.py
pycricinfo/api/endpoints/play_by_play.py
pycricinfo/api/endpoints/player.py
pycricinfo/api/endpoints/raw.py
pycricinfo/api/endpoints/scorecard.py
pycricinfo/api/endpoints/seasons.py
pycricinfo/api/endpoints/team.py
pycricinfo/cricinfo/api_helper.py
pycricinfo/cricinfo/call_cricinfo_api.py
pycricinfo/output_models/__init__.py
pycricinfo/output_models/ball_by_ball_page.py
pycricinfo/output_models/common.py
pycricinfo/output_models/innings.py
pycricinfo/output_models/scorecard.py
pycricinfo/search/__init__.py
pycricinfo/search/seasons.py
pycricinfo/search/series.py
pycricinfo/source_models/__init__.py
pycricinfo/source_models/api/athelete.py
pycricinfo/source_models/api/batting.py
pycricinfo/source_models/api/bowling.py
pycricinfo/source_models/api/commentary.py
pycricinfo/source_models/api/common.py
pycricinfo/source_models/api/dismissal.py
pycricinfo/source_models/api/league.py
pycricinfo/source_models/api/linescores.py
pycricinfo/source_models/api/match.py
pycricinfo/source_models/api/match_basic.py
pycricinfo/source_models/api/match_note.py
pycricinfo/source_models/api/official.py
pycricinfo/source_models/api/player.py
pycricinfo/source_models/api/roster.py
pycricinfo/source_models/api/statistics.py
pycricinfo/source_models/api/team.py
pycricinfo/source_models/api/venue.py
pycricinfo/source_models/pages/series.py
pycricinfo-0.0.21.dist-info/METADATA
pycricinfo-0.0.21.dist-info/WHEEL
pycricinfo-0.0.21.dist-info/entry_points.txt
pycricinfo-0.0.21.dist-info/licenses/LICENSE
pycricinfo-0.0.21.dist-info/RECORD
