Metadata-Version: 2.4
Name: pycricinfo
Version: 0.0.21
Summary: An API using pycricinfo to collect data from ESPN Cricinfo
Project-URL: Homepage, https://github.com/mattholland0202/py-cricinfo
Project-URL: Source, https://github.com/mattholland0202/py-cricinfo
Author: Matt Holland
License: MIT
License-File: LICENSE
Classifier: Intended Audience :: Developers
Classifier: License :: OSI Approved :: MIT License
Classifier: Operating System :: OS Independent
Classifier: Programming Language :: Python
Classifier: Programming Language :: Python :: 3
Classifier: Programming Language :: Python :: 3.13
Requires-Python: >=3.13
Requires-Dist: beautifulsoup4>=4.13.4
Requires-Dist: fastapi-pagination>=0.14.0
Requires-Dist: prettytable>=3.16.0
Requires-Dist: pydantic-settings>=2.9.1
Requires-Dist: pydantic>=2.11.5
Requires-Dist: requests>=2.32.3
Requires-Dist: rich>=14.2.0
Provides-Extra: api
Requires-Dist: fastapi-pagination>=0.15.0; extra == 'api'
Requires-Dist: fastapi>=0.115.12; extra == 'api'
Requires-Dist: uvicorn>=0.34.2; extra == 'api'
Provides-Extra: dev
Requires-Dist: pytest>=8.4.1; extra == 'dev'
Requires-Dist: ruff>=0.11.0; extra == 'dev'
